xurrent/__init__.py
xurrent/configuration_items.py
xurrent/core.py
xurrent/people.py
xurrent/requests.py
xurrent/tasks.py
xurrent/teams.py
xurrent/workflows.py
xurrent-0.10.0.dist-info/LICENSE
xurrent-0.10.0.dist-info/METADATA
xurrent-0.10.0.dist-info/WHEEL
xurrent-0.10.0.dist-info/RECORD
