Metadata-Version: 2.3
Name: xurrent
Version: 0.10.0
Summary: A python module to interact with the Xurrent API.
Author: Fabian Steiner
Author-email: fabian@stei-ner.net
Requires-Python: >=3.9
Classifier: Programming Language :: Python :: 3
Classifier: License :: OSI Approved :: MIT License
Classifier: Operating System :: OS Independent
Requires-Dist: requests (>=2.32.3,<3.0.0)
Project-URL: Homepage, https://github.com/fasteiner/xurrent-python
Project-URL: Issues, https://github.com/fasteiner/xurrent-python/issues
